{
	"partitions" : [
		{
			"name" : "Top",
			"pins" : [
				{
					"name" : "iaddr[0]",
					"strict" : false
				},
				{
					"name" : "iaddr[1]",
					"strict" : false
				},
				{
					"name" : "iaddr[2]",
					"strict" : false
				},
				{
					"name" : "iaddr[3]",
					"strict" : false
				},
				{
					"name" : "iaddr[4]",
					"strict" : false
				},
				{
					"name" : "iaddr[5]",
					"strict" : false
				},
				{
					"name" : "iaddr[6]",
					"strict" : false
				},
				{
					"name" : "iaddr[7]",
					"strict" : false
				},
				{
					"name" : "iaddr[8]",
					"strict" : false
				},
				{
					"name" : "iaddr[9]",
					"strict" : false
				},
				{
					"name" : "ddata_w[0]",
					"strict" : false
				},
				{
					"name" : "ddata_w[1]",
					"strict" : false
				},
				{
					"name" : "ddata_w[2]",
					"strict" : false
				},
				{
					"name" : "ddata_w[3]",
					"strict" : false
				},
				{
					"name" : "ddata_w[4]",
					"strict" : false
				},
				{
					"name" : "ddata_w[5]",
					"strict" : false
				},
				{
					"name" : "ddata_w[6]",
					"strict" : false
				},
				{
					"name" : "ddata_w[7]",
					"strict" : false
				},
				{
					"name" : "ddata_w[8]",
					"strict" : false
				},
				{
					"name" : "ddata_w[9]",
					"strict" : false
				},
				{
					"name" : "ddata_w[10]",
					"strict" : false
				},
				{
					"name" : "ddata_w[11]",
					"strict" : false
				},
				{
					"name" : "ddata_w[12]",
					"strict" : false
				},
				{
					"name" : "ddata_w[13]",
					"strict" : false
				},
				{
					"name" : "ddata_w[14]",
					"strict" : false
				},
				{
					"name" : "ddata_w[15]",
					"strict" : false
				},
				{
					"name" : "ddata_w[16]",
					"strict" : false
				},
				{
					"name" : "ddata_w[17]",
					"strict" : false
				},
				{
					"name" : "ddata_w[18]",
					"strict" : false
				},
				{
					"name" : "ddata_w[19]",
					"strict" : false
				},
				{
					"name" : "ddata_w[20]",
					"strict" : false
				},
				{
					"name" : "ddata_w[21]",
					"strict" : false
				},
				{
					"name" : "ddata_w[22]",
					"strict" : false
				},
				{
					"name" : "ddata_w[23]",
					"strict" : false
				},
				{
					"name" : "ddata_w[24]",
					"strict" : false
				},
				{
					"name" : "ddata_w[25]",
					"strict" : false
				},
				{
					"name" : "ddata_w[26]",
					"strict" : false
				},
				{
					"name" : "ddata_w[27]",
					"strict" : false
				},
				{
					"name" : "ddata_w[28]",
					"strict" : false
				},
				{
					"name" : "ddata_w[29]",
					"strict" : false
				},
				{
					"name" : "ddata_w[30]",
					"strict" : false
				},
				{
					"name" : "ddata_w[31]",
					"strict" : false
				},
				{
					"name" : "MemRead",
					"strict" : false
				},
				{
					"name" : "MemWrite",
					"strict" : false
				},
				{
					"name" : "cableALUmux[0]",
					"strict" : false
				},
				{
					"name" : "cableALUmux[1]",
					"strict" : false
				},
				{
					"name" : "cableALUmux[2]",
					"strict" : false
				},
				{
					"name" : "cableALUmux[3]",
					"strict" : false
				},
				{
					"name" : "cableALUmux[4]",
					"strict" : false
				},
				{
					"name" : "cableALUmux[5]",
					"strict" : false
				},
				{
					"name" : "cableALUmux[6]",
					"strict" : false
				},
				{
					"name" : "cableALUmux[7]",
					"strict" : false
				},
				{
					"name" : "cableALUmux[8]",
					"strict" : false
				},
				{
					"name" : "cableALUmux[9]",
					"strict" : false
				},
				{
					"name" : "cableALUmux[10]",
					"strict" : false
				},
				{
					"name" : "cableALUmux[11]",
					"strict" : false
				},
				{
					"name" : "cableALUmux[12]",
					"strict" : false
				},
				{
					"name" : "cableALUmux[13]",
					"strict" : false
				},
				{
					"name" : "cableALUmux[14]",
					"strict" : false
				},
				{
					"name" : "cableALUmux[15]",
					"strict" : false
				},
				{
					"name" : "cableALUmux[16]",
					"strict" : false
				},
				{
					"name" : "cableALUmux[17]",
					"strict" : false
				},
				{
					"name" : "cableALUmux[18]",
					"strict" : false
				},
				{
					"name" : "cableALUmux[19]",
					"strict" : false
				},
				{
					"name" : "cableALUmux[20]",
					"strict" : false
				},
				{
					"name" : "cableALUmux[21]",
					"strict" : false
				},
				{
					"name" : "cableALUmux[22]",
					"strict" : false
				},
				{
					"name" : "cableALUmux[23]",
					"strict" : false
				},
				{
					"name" : "cableALUmux[24]",
					"strict" : false
				},
				{
					"name" : "cableALUmux[25]",
					"strict" : false
				},
				{
					"name" : "cableALUmux[26]",
					"strict" : false
				},
				{
					"name" : "cableALUmux[27]",
					"strict" : false
				},
				{
					"name" : "cableALUmux[28]",
					"strict" : false
				},
				{
					"name" : "cableALUmux[29]",
					"strict" : false
				},
				{
					"name" : "cableALUmux[30]",
					"strict" : false
				},
				{
					"name" : "cableALUmux[31]",
					"strict" : false
				},
				{
					"name" : "idata[22]",
					"strict" : false
				},
				{
					"name" : "idata[23]",
					"strict" : false
				},
				{
					"name" : "idata[21]",
					"strict" : false
				},
				{
					"name" : "idata[20]",
					"strict" : false
				},
				{
					"name" : "idata[24]",
					"strict" : false
				},
				{
					"name" : "idata[0]",
					"strict" : false
				},
				{
					"name" : "idata[1]",
					"strict" : false
				},
				{
					"name" : "idata[2]",
					"strict" : false
				},
				{
					"name" : "idata[3]",
					"strict" : false
				},
				{
					"name" : "idata[6]",
					"strict" : false
				},
				{
					"name" : "idata[4]",
					"strict" : false
				},
				{
					"name" : "idata[5]",
					"strict" : false
				},
				{
					"name" : "idata[12]",
					"strict" : false
				},
				{
					"name" : "idata[13]",
					"strict" : false
				},
				{
					"name" : "idata[14]",
					"strict" : false
				},
				{
					"name" : "idata[30]",
					"strict" : false
				},
				{
					"name" : "idata[31]",
					"strict" : false
				},
				{
					"name" : "idata[17]",
					"strict" : false
				},
				{
					"name" : "idata[18]",
					"strict" : false
				},
				{
					"name" : "idata[15]",
					"strict" : false
				},
				{
					"name" : "idata[16]",
					"strict" : false
				},
				{
					"name" : "idata[19]",
					"strict" : false
				},
				{
					"name" : "idata[29]",
					"strict" : false
				},
				{
					"name" : "idata[28]",
					"strict" : false
				},
				{
					"name" : "idata[27]",
					"strict" : false
				},
				{
					"name" : "idata[26]",
					"strict" : false
				},
				{
					"name" : "idata[25]",
					"strict" : false
				},
				{
					"name" : "idata[11]",
					"strict" : false
				},
				{
					"name" : "idata[10]",
					"strict" : false
				},
				{
					"name" : "idata[9]",
					"strict" : false
				},
				{
					"name" : "idata[8]",
					"strict" : false
				},
				{
					"name" : "idata[7]",
					"strict" : false
				},
				{
					"name" : "CLK",
					"strict" : false
				},
				{
					"name" : "RESET_N",
					"strict" : false
				},
				{
					"name" : "ddata_r[0]",
					"strict" : false
				},
				{
					"name" : "ddata_r[1]",
					"strict" : false
				},
				{
					"name" : "ddata_r[2]",
					"strict" : false
				},
				{
					"name" : "ddata_r[3]",
					"strict" : false
				},
				{
					"name" : "ddata_r[4]",
					"strict" : false
				},
				{
					"name" : "ddata_r[5]",
					"strict" : false
				},
				{
					"name" : "ddata_r[6]",
					"strict" : false
				},
				{
					"name" : "ddata_r[7]",
					"strict" : false
				},
				{
					"name" : "ddata_r[8]",
					"strict" : false
				},
				{
					"name" : "ddata_r[9]",
					"strict" : false
				},
				{
					"name" : "ddata_r[10]",
					"strict" : false
				},
				{
					"name" : "ddata_r[11]",
					"strict" : false
				},
				{
					"name" : "ddata_r[12]",
					"strict" : false
				},
				{
					"name" : "ddata_r[13]",
					"strict" : false
				},
				{
					"name" : "ddata_r[14]",
					"strict" : false
				},
				{
					"name" : "ddata_r[15]",
					"strict" : false
				},
				{
					"name" : "ddata_r[16]",
					"strict" : false
				},
				{
					"name" : "ddata_r[17]",
					"strict" : false
				},
				{
					"name" : "ddata_r[18]",
					"strict" : false
				},
				{
					"name" : "ddata_r[19]",
					"strict" : false
				},
				{
					"name" : "ddata_r[20]",
					"strict" : false
				},
				{
					"name" : "ddata_r[21]",
					"strict" : false
				},
				{
					"name" : "ddata_r[22]",
					"strict" : false
				},
				{
					"name" : "ddata_r[23]",
					"strict" : false
				},
				{
					"name" : "ddata_r[24]",
					"strict" : false
				},
				{
					"name" : "ddata_r[25]",
					"strict" : false
				},
				{
					"name" : "ddata_r[26]",
					"strict" : false
				},
				{
					"name" : "ddata_r[27]",
					"strict" : false
				},
				{
					"name" : "ddata_r[28]",
					"strict" : false
				},
				{
					"name" : "ddata_r[29]",
					"strict" : false
				},
				{
					"name" : "ddata_r[30]",
					"strict" : false
				},
				{
					"name" : "ddata_r[31]",
					"strict" : false
				}
			]
		}
	]
}